Metadata-Version: 1.0
Name: calculator-python
Version: 0.1.0
Summary: Calculator revers polish notation
Home-page: UNKNOWN
Author: UNKNOWN
Author-email: UNKNOWN
License: UNKNOWN
Platform: UNKNOWN
